[{"bottomright": {"x": 424, "y": 660}, "confidence": 0.75, "topleft": {"x": 238, "y": 209}, "label": "person"}, {"bottomright": {"x": 900, "y": 592}, "confidence": 0.72, "topleft": {"x": 674, "y": 268}, "label": "person"}, {"bottomright": {"x": 514, "y": 626}, "confidence": 0.62, "topleft": {"x": 401, "y": 329}, "label": "person"}, {"bottomright": {"x": 573, "y": 650}, "confidence": 0.14, "topleft": {"x": 447, "y": 364}, "label": "person"}, {"bottomright": {"x": 641, "y": 654}, "confidence": 0.62, "topleft": {"x": 508, "y": 362}, "label": "person"}, {"bottomright": {"x": 709, "y": 668}, "confidence": 0.42, "topleft": {"x": 578, "y": 352}, "label": "person"}, {"bottomright": {"x": 1081, "y": 289}, "confidence": 0.13, "topleft": {"x": 953, "y": 203}, "label": "cake"}, {"bottomright": {"x": 342, "y": 640}, "confidence": 0.14, "topleft": {"x": 292, "y": 456}, "label": "chair"}, {"bottomright": {"x": 424, "y": 653}, "confidence": 0.13, "topleft": {"x": 323, "y": 437}, "label": "chair"}, {"bottomright": {"x": 908, "y": 653}, "confidence": 0.25, "topleft": {"x": 679, "y": 432}, "label": "chair"}, {"bottomright": {"x": 476, "y": 644}, "confidence": 0.14, "topleft": {"x": 397, "y": 514}, "label": "chair"}, {"bottomright": {"x": 538, "y": 642}, "confidence": 0.2, "topleft": {"x": 473, "y": 520}, "label": "chair"}]