[{"bottomright": {"x": 894, "y": 149}, "confidence": 0.14, "topleft": {"x": 817, "y": 87}, "label": "person"}, {"bottomright": {"x": 460, "y": 719}, "confidence": 0.12, "topleft": {"x": 16, "y": 64}, "label": "person"}, {"bottomright": {"x": 1046, "y": 636}, "confidence": 0.14, "topleft": {"x": 896, "y": 154}, "label": "person"}, {"bottomright": {"x": 1269, "y": 706}, "confidence": 0.49, "topleft": {"x": 939, "y": 150}, "label": "person"}, {"bottomright": {"x": 456, "y": 719}, "confidence": 0.14, "topleft": {"x": 270, "y": 287}, "label": "person"}]