[{"caption": "the man in a white wall", "predicate": "in", "target": {"coordinates": [522.27691650391, -0.16831970214844, 205.10241699219, 372.205078125]}, "name": 153, "source": {"coordinates": [261.39367675781, 1.4691009521484, 395.63659667969, 403.26800537109]}, "seconds": 6.375, "object": "a white wall", "type": "relation", "subject": "the man"}, {"caption": "the man has head", "predicate": "has", "target": {"coordinates": [20.901016235352, 6.4042053222656, 399.25384521484, 396.50543212891]}, "name": 153, "source": {"coordinates": [261.39367675781, 1.4691009521484, 395.63659667969, 403.26800537109]}, "seconds": 6.375, "object": "head", "type": "relation", "subject": "the man"}, {"caption": "the man wearing black shirt", "predicate": "wearing", "target": {"coordinates": [363.16442871094, 7.6010513305664, 166.87774658203, 130.93502807617]}, "name": 153, "source": {"coordinates": [261.39367675781, 1.4691009521484, 395.63659667969, 403.26800537109]}, "seconds": 6.375, "object": "black shirt", "type": "relation", "subject": "the man"}, {"caption": "the man wearing black shirt", "predicate": "wearing", "target": {"coordinates": [261.39367675781, 1.4691009521484, 395.63659667969, 403.26800537109]}, "name": 153, "source": {"coordinates": [522.27691650391, -0.16831970214844, 205.10241699219, 372.205078125]}, "seconds": 6.375, "object": "black shirt", "type": "relation", "subject": "the man"}, {"caption": "the man wearing black shirt", "predicate": "wearing", "target": {"coordinates": [20.901016235352, 6.4042053222656, 399.25384521484, 396.50543212891]}, "name": 153, "source": {"coordinates": [522.27691650391, -0.16831970214844, 205.10241699219, 372.205078125]}, "seconds": 6.375, "object": "black shirt", "type": "relation", "subject": "the man"}, {"caption": "the man wearing black shirt", "predicate": "wearing", "target": {"coordinates": [363.16442871094, 7.6010513305664, 166.87774658203, 130.93502807617]}, "name": 153, "source": {"coordinates": [522.27691650391, -0.16831970214844, 205.10241699219, 372.205078125]}, "seconds": 6.375, "object": "black shirt", "type": "relation", "subject": "the man"}, {"caption": "the man wearing black shirt", "predicate": "wearing", "target": {"coordinates": [261.39367675781, 1.4691009521484, 395.63659667969, 403.26800537109]}, "name": 153, "source": {"coordinates": [20.901016235352, 6.4042053222656, 399.25384521484, 396.50543212891]}, "seconds": 6.375, "object": "black shirt", "type": "relation", "subject": "the man"}, {"caption": "the man wearing black shirt", "predicate": "wearing", "target": {"coordinates": [522.27691650391, -0.16831970214844, 205.10241699219, 372.205078125]}, "name": 153, "source": {"coordinates": [20.901016235352, 6.4042053222656, 399.25384521484, 396.50543212891]}, "seconds": 6.375, "object": "black shirt", "type": "relation", "subject": "the man"}, {"caption": "the head of man", "predicate": "of", "target": {"coordinates": [363.16442871094, 7.6010513305664, 166.87774658203, 130.93502807617]}, "name": 153, "source": {"coordinates": [20.901016235352, 6.4042053222656, 399.25384521484, 396.50543212891]}, "seconds": 6.375, "object": "man", "type": "relation", "subject": "the head"}, {"caption": "the head of man", "predicate": "of", "target": {"coordinates": [261.39367675781, 1.4691009521484, 395.63659667969, 403.26800537109]}, "name": 153, "source": {"coordinates": [363.16442871094, 7.6010513305664, 166.87774658203, 130.93502807617]}, "seconds": 6.375, "object": "man", "type": "relation", "subject": "the head"}, {"caption": "the man wearing black shirt", "predicate": "wearing", "target": {"coordinates": [522.27691650391, -0.16831970214844, 205.10241699219, 372.205078125]}, "name": 153, "source": {"coordinates": [363.16442871094, 7.6010513305664, 166.87774658203, 130.93502807617]}, "seconds": 6.375, "object": "black shirt", "type": "relation", "subject": "the man"}, {"caption": "the man in a white wall", "predicate": "in", "target": {"coordinates": [20.901016235352, 6.4042053222656, 399.25384521484, 396.50543212891]}, "name": 153, "source": {"coordinates": [363.16442871094, 7.6010513305664, 166.87774658203, 130.93502807617]}, "seconds": 6.375, "object": "a white wall", "type": "relation", "subject": "the man"}]