[{"caption": "the man wearing black shirt", "predicate": "wearing", "target": {"coordinates": [346.74032592773, 96.729339599609, 190.46060180664, 300.85144042969]}, "name": 162, "source": {"coordinates": [24.223693847656, 40.272964477539, 698.95989990234, 377.94714355469]}, "seconds": 6.75, "object": "black shirt", "type": "relation", "subject": "the man"}, {"caption": "the man has black hair", "predicate": "has", "target": {"coordinates": [214.47155761719, 61.551193237305, 194.03814697266, 342.97064208984]}, "name": 162, "source": {"coordinates": [24.223693847656, 40.272964477539, 698.95989990234, 377.94714355469]}, "seconds": 6.75, "object": "black hair", "type": "relation", "subject": "the man"}, {"caption": "the man wearing white shirt", "predicate": "wearing", "target": {"coordinates": [327.78262329102, 329.08309936523, 57.019287109375, 56.166625976562]}, "name": 162, "source": {"coordinates": [24.223693847656, 40.272964477539, 698.95989990234, 377.94714355469]}, "seconds": 6.75, "object": "white shirt", "type": "relation", "subject": "the man"}, {"caption": "the man has white shirt", "predicate": "has", "target": {"coordinates": [7.5440368652344, -4.0870895385742, 392.7375793457, 193.44567871094]}, "name": 162, "source": {"coordinates": [24.223693847656, 40.272964477539, 698.95989990234, 377.94714355469]}, "seconds": 6.75, "object": "white shirt", "type": "relation", "subject": "the man"}, {"caption": "the man in white shirt", "predicate": "in", "target": {"coordinates": [257.05209350586, 182.48709106445, 104.06707763672, 42.362121582031]}, "name": 162, "source": {"coordinates": [24.223693847656, 40.272964477539, 698.95989990234, 377.94714355469]}, "seconds": 6.75, "object": "white shirt", "type": "relation", "subject": "the man"}, {"caption": "the man wearing white shirt", "predicate": "wearing", "target": {"coordinates": [-4.14404296875, 130.69808959961, 306.71984863281, 271.47229003906]}, "name": 162, "source": {"coordinates": [24.223693847656, 40.272964477539, 698.95989990234, 377.94714355469]}, "seconds": 6.75, "object": "white shirt", "type": "relation", "subject": "the man"}, {"caption": "the man in white shirt", "predicate": "in", "target": {"coordinates": [316.17938232422, -2.8643417358398, 414.04016113281, 211.18438720703]}, "name": 162, "source": {"coordinates": [24.223693847656, 40.272964477539, 698.95989990234, 377.94714355469]}, "seconds": 6.75, "object": "white shirt", "type": "relation", "subject": "the man"}, {"caption": "the man in white shirt", "predicate": "in", "target": {"coordinates": [24.223693847656, 40.272964477539, 698.95989990234, 377.94714355469]}, "name": 162, "source": {"coordinates": [346.74032592773, 96.729339599609, 190.46060180664, 300.85144042969]}, "seconds": 6.75, "object": "white shirt", "type": "relation", "subject": "the man"}, {"caption": "the man has black handle", "predicate": "has", "target": {"coordinates": [214.47155761719, 61.551193237305, 194.03814697266, 342.97064208984]}, "name": 162, "source": {"coordinates": [346.74032592773, 96.729339599609, 190.46060180664, 300.85144042969]}, "seconds": 6.75, "object": "black handle", "type": "relation", "subject": "the man"}, {"caption": "the man in white shirt", "predicate": "in", "target": {"coordinates": [327.78262329102, 329.08309936523, 57.019287109375, 56.166625976562]}, "name": 162, "source": {"coordinates": [346.74032592773, 96.729339599609, 190.46060180664, 300.85144042969]}, "seconds": 6.75, "object": "white shirt", "type": "relation", "subject": "the man"}, {"caption": "the man wearing white shirt", "predicate": "wearing", "target": {"coordinates": [7.5440368652344, -4.0870895385742, 392.7375793457, 193.44567871094]}, "name": 162, "source": {"coordinates": [346.74032592773, 96.729339599609, 190.46060180664, 300.85144042969]}, "seconds": 6.75, "object": "white shirt", "type": "relation", "subject": "the man"}, {"caption": "the man wearing white shirt", "predicate": "wearing", "target": {"coordinates": [257.05209350586, 182.48709106445, 104.06707763672, 42.362121582031]}, "name": 162, "source": {"coordinates": [346.74032592773, 96.729339599609, 190.46060180664, 300.85144042969]}, "seconds": 6.75, "object": "white shirt", "type": "relation", "subject": "the man"}, {"caption": "the man wearing white shirt", "predicate": "wearing", "target": {"coordinates": [-4.14404296875, 130.69808959961, 306.71984863281, 271.47229003906]}, "name": 162, "source": {"coordinates": [346.74032592773, 96.729339599609, 190.46060180664, 300.85144042969]}, "seconds": 6.75, "object": "white shirt", "type": "relation", "subject": "the man"}, {"caption": "the man in white shirt", "predicate": "in", "target": {"coordinates": [316.17938232422, -2.8643417358398, 414.04016113281, 211.18438720703]}, "name": 162, "source": {"coordinates": [346.74032592773, 96.729339599609, 190.46060180664, 300.85144042969]}, "seconds": 6.75, "object": "white shirt", "type": "relation", "subject": "the man"}, {"caption": "the man in white shirt", "predicate": "in", "target": {"coordinates": [24.223693847656, 40.272964477539, 698.95989990234, 377.94714355469]}, "name": 162, "source": {"coordinates": [214.47155761719, 61.551193237305, 194.03814697266, 342.97064208984]}, "seconds": 6.75, "object": "white shirt", "type": "relation", "subject": "the man"}, {"caption": "the man wearing black shirt", "predicate": "wearing", "target": {"coordinates": [346.74032592773, 96.729339599609, 190.46060180664, 300.85144042969]}, "name": 162, "source": {"coordinates": [214.47155761719, 61.551193237305, 194.03814697266, 342.97064208984]}, "seconds": 6.75, "object": "black shirt", "type": "relation", "subject": "the man"}, {"caption": "the man in white shirt", "predicate": "in", "target": {"coordinates": [327.78262329102, 329.08309936523, 57.019287109375, 56.166625976562]}, "name": 162, "source": {"coordinates": [214.47155761719, 61.551193237305, 194.03814697266, 342.97064208984]}, "seconds": 6.75, "object": "white shirt", "type": "relation", "subject": "the man"}, {"caption": "the man has white shirt", "predicate": "has", "target": {"coordinates": [7.5440368652344, -4.0870895385742, 392.7375793457, 193.44567871094]}, "name": 162, "source": {"coordinates": [214.47155761719, 61.551193237305, 194.03814697266, 342.97064208984]}, "seconds": 6.75, "object": "white shirt", "type": "relation", "subject": "the man"}, {"caption": "the man wearing white shirt", "predicate": "wearing", "target": {"coordinates": [257.05209350586, 182.48709106445, 104.06707763672, 42.362121582031]}, "name": 162, "source": {"coordinates": [214.47155761719, 61.551193237305, 194.03814697266, 342.97064208984]}, "seconds": 6.75, "object": "white shirt", "type": "relation", "subject": "the man"}, {"caption": "the man wearing white shirt", "predicate": "wearing", "target": {"coordinates": [-4.14404296875, 130.69808959961, 306.71984863281, 271.47229003906]}, "name": 162, "source": {"coordinates": [214.47155761719, 61.551193237305, 194.03814697266, 342.97064208984]}, "seconds": 6.75, "object": "white shirt", "type": "relation", "subject": "the man"}, {"caption": "the hand on white shirt", "predicate": "on", "target": {"coordinates": [316.17938232422, -2.8643417358398, 414.04016113281, 211.18438720703]}, "name": 162, "source": {"coordinates": [214.47155761719, 61.551193237305, 194.03814697266, 342.97064208984]}, "seconds": 6.75, "object": "white shirt", "type": "relation", "subject": "the hand"}, {"caption": "the hand on white shirt", "predicate": "on", "target": {"coordinates": [24.223693847656, 40.272964477539, 698.95989990234, 377.94714355469]}, "name": 162, "source": {"coordinates": [327.78262329102, 329.08309936523, 57.019287109375, 56.166625976562]}, "seconds": 6.75, "object": "white shirt", "type": "relation", "subject": "the hand"}, {"caption": "the hand on white shirt", "predicate": "on", "target": {"coordinates": [346.74032592773, 96.729339599609, 190.46060180664, 300.85144042969]}, "name": 162, "source": {"coordinates": [327.78262329102, 329.08309936523, 57.019287109375, 56.166625976562]}, "seconds": 6.75, "object": "white shirt", "type": "relation", "subject": "the hand"}, {"caption": "the hand on man", "predicate": "on", "target": {"coordinates": [214.47155761719, 61.551193237305, 194.03814697266, 342.97064208984]}, "name": 162, "source": {"coordinates": [327.78262329102, 329.08309936523, 57.019287109375, 56.166625976562]}, "seconds": 6.75, "object": "man", "type": "relation", "subject": "the hand"}, {"caption": "the hand on white shirt", "predicate": "on", "target": {"coordinates": [7.5440368652344, -4.0870895385742, 392.7375793457, 193.44567871094]}, "name": 162, "source": {"coordinates": [327.78262329102, 329.08309936523, 57.019287109375, 56.166625976562]}, "seconds": 6.75, "object": "white shirt", "type": "relation", "subject": "the hand"}, {"caption": "the hand on white shirt", "predicate": "on", "target": {"coordinates": [257.05209350586, 182.48709106445, 104.06707763672, 42.362121582031]}, "name": 162, "source": {"coordinates": [327.78262329102, 329.08309936523, 57.019287109375, 56.166625976562]}, "seconds": 6.75, "object": "white shirt", "type": "relation", "subject": "the hand"}, {"caption": "the hand on white shirt", "predicate": "on", "target": {"coordinates": [-4.14404296875, 130.69808959961, 306.71984863281, 271.47229003906]}, "name": 162, "source": {"coordinates": [327.78262329102, 329.08309936523, 57.019287109375, 56.166625976562]}, "seconds": 6.75, "object": "white shirt", "type": "relation", "subject": "the hand"}, {"caption": "the man in white shirt", "predicate": "in", "target": {"coordinates": [316.17938232422, -2.8643417358398, 414.04016113281, 211.18438720703]}, "name": 162, "source": {"coordinates": [327.78262329102, 329.08309936523, 57.019287109375, 56.166625976562]}, "seconds": 6.75, "object": "white shirt", "type": "relation", "subject": "the man"}, {"caption": "the man in white shirt", "predicate": "in", "target": {"coordinates": [24.223693847656, 40.272964477539, 698.95989990234, 377.94714355469]}, "name": 162, "source": {"coordinates": [7.5440368652344, -4.0870895385742, 392.7375793457, 193.44567871094]}, "seconds": 6.75, "object": "white shirt", "type": "relation", "subject": "the man"}, {"caption": "the man wearing black shirt", "predicate": "wearing", "target": {"coordinates": [346.74032592773, 96.729339599609, 190.46060180664, 300.85144042969]}, "name": 162, "source": {"coordinates": [7.5440368652344, -4.0870895385742, 392.7375793457, 193.44567871094]}, "seconds": 6.75, "object": "black shirt", "type": "relation", "subject": "the man"}, {"caption": "the man wearing black shirt", "predicate": "wearing", "target": {"coordinates": [214.47155761719, 61.551193237305, 194.03814697266, 342.97064208984]}, "name": 162, "source": {"coordinates": [7.5440368652344, -4.0870895385742, 392.7375793457, 193.44567871094]}, "seconds": 6.75, "object": "black shirt", "type": "relation", "subject": "the man"}, {"caption": "the man wearing black shirt", "predicate": "wearing", "target": {"coordinates": [327.78262329102, 329.08309936523, 57.019287109375, 56.166625976562]}, "name": 162, "source": {"coordinates": [7.5440368652344, -4.0870895385742, 392.7375793457, 193.44567871094]}, "seconds": 6.75, "object": "black shirt", "type": "relation", "subject": "the man"}, {"caption": "the man in white shirt", "predicate": "in", "target": {"coordinates": [257.05209350586, 182.48709106445, 104.06707763672, 42.362121582031]}, "name": 162, "source": {"coordinates": [7.5440368652344, -4.0870895385742, 392.7375793457, 193.44567871094]}, "seconds": 6.75, "object": "white shirt", "type": "relation", "subject": "the man"}, {"caption": "the man wearing white shirt", "predicate": "wearing", "target": {"coordinates": [-4.14404296875, 130.69808959961, 306.71984863281, 271.47229003906]}, "name": 162, "source": {"coordinates": [7.5440368652344, -4.0870895385742, 392.7375793457, 193.44567871094]}, "seconds": 6.75, "object": "white shirt", "type": "relation", "subject": "the man"}, {"caption": "the logo on white shirt", "predicate": "on", "target": {"coordinates": [316.17938232422, -2.8643417358398, 414.04016113281, 211.18438720703]}, "name": 162, "source": {"coordinates": [7.5440368652344, -4.0870895385742, 392.7375793457, 193.44567871094]}, "seconds": 6.75, "object": "white shirt", "type": "relation", "subject": "the logo"}, {"caption": "the logo on white shirt", "predicate": "on", "target": {"coordinates": [24.223693847656, 40.272964477539, 698.95989990234, 377.94714355469]}, "name": 162, "source": {"coordinates": [257.05209350586, 182.48709106445, 104.06707763672, 42.362121582031]}, "seconds": 6.75, "object": "white shirt", "type": "relation", "subject": "the logo"}, {"caption": "the logo on white shirt", "predicate": "on", "target": {"coordinates": [346.74032592773, 96.729339599609, 190.46060180664, 300.85144042969]}, "name": 162, "source": {"coordinates": [257.05209350586, 182.48709106445, 104.06707763672, 42.362121582031]}, "seconds": 6.75, "object": "white shirt", "type": "relation", "subject": "the logo"}, {"caption": "the logo on white shirt", "predicate": "on", "target": {"coordinates": [214.47155761719, 61.551193237305, 194.03814697266, 342.97064208984]}, "name": 162, "source": {"coordinates": [257.05209350586, 182.48709106445, 104.06707763672, 42.362121582031]}, "seconds": 6.75, "object": "white shirt", "type": "relation", "subject": "the logo"}, {"caption": "the logo on white shirt", "predicate": "on", "target": {"coordinates": [327.78262329102, 329.08309936523, 57.019287109375, 56.166625976562]}, "name": 162, "source": {"coordinates": [257.05209350586, 182.48709106445, 104.06707763672, 42.362121582031]}, "seconds": 6.75, "object": "white shirt", "type": "relation", "subject": "the logo"}, {"caption": "the logo on white shirt", "predicate": "on", "target": {"coordinates": [7.5440368652344, -4.0870895385742, 392.7375793457, 193.44567871094]}, "name": 162, "source": {"coordinates": [257.05209350586, 182.48709106445, 104.06707763672, 42.362121582031]}, "seconds": 6.75, "object": "white shirt", "type": "relation", "subject": "the logo"}, {"caption": "the logo on white shirt", "predicate": "on", "target": {"coordinates": [-4.14404296875, 130.69808959961, 306.71984863281, 271.47229003906]}, "name": 162, "source": {"coordinates": [257.05209350586, 182.48709106445, 104.06707763672, 42.362121582031]}, "seconds": 6.75, "object": "white shirt", "type": "relation", "subject": "the logo"}, {"caption": "the white clouds in blue sky", "predicate": "in", "target": {"coordinates": [316.17938232422, -2.8643417358398, 414.04016113281, 211.18438720703]}, "name": 162, "source": {"coordinates": [257.05209350586, 182.48709106445, 104.06707763672, 42.362121582031]}, "seconds": 6.75, "object": "blue sky", "type": "relation", "subject": "the white clouds"}, {"caption": "the white clouds in blue sky", "predicate": "in", "target": {"coordinates": [24.223693847656, 40.272964477539, 698.95989990234, 377.94714355469]}, "name": 162, "source": {"coordinates": [-4.14404296875, 130.69808959961, 306.71984863281, 271.47229003906]}, "seconds": 6.75, "object": "blue sky", "type": "relation", "subject": "the white clouds"}, {"caption": "the man wearing white shirt", "predicate": "wearing", "target": {"coordinates": [346.74032592773, 96.729339599609, 190.46060180664, 300.85144042969]}, "name": 162, "source": {"coordinates": [-4.14404296875, 130.69808959961, 306.71984863281, 271.47229003906]}, "seconds": 6.75, "object": "white shirt", "type": "relation", "subject": "the man"}, {"caption": "the man wearing black shirt", "predicate": "wearing", "target": {"coordinates": [214.47155761719, 61.551193237305, 194.03814697266, 342.97064208984]}, "name": 162, "source": {"coordinates": [-4.14404296875, 130.69808959961, 306.71984863281, 271.47229003906]}, "seconds": 6.75, "object": "black shirt", "type": "relation", "subject": "the man"}, {"caption": "the man wearing black shirt", "predicate": "wearing", "target": {"coordinates": [327.78262329102, 329.08309936523, 57.019287109375, 56.166625976562]}, "name": 162, "source": {"coordinates": [-4.14404296875, 130.69808959961, 306.71984863281, 271.47229003906]}, "seconds": 6.75, "object": "black shirt", "type": "relation", "subject": "the man"}, {"caption": "the man wearing white shirt", "predicate": "wearing", "target": {"coordinates": [7.5440368652344, -4.0870895385742, 392.7375793457, 193.44567871094]}, "name": 162, "source": {"coordinates": [-4.14404296875, 130.69808959961, 306.71984863281, 271.47229003906]}, "seconds": 6.75, "object": "white shirt", "type": "relation", "subject": "the man"}, {"caption": "the man wearing white shirt", "predicate": "wearing", "target": {"coordinates": [257.05209350586, 182.48709106445, 104.06707763672, 42.362121582031]}, "name": 162, "source": {"coordinates": [-4.14404296875, 130.69808959961, 306.71984863281, 271.47229003906]}, "seconds": 6.75, "object": "white shirt", "type": "relation", "subject": "the man"}, {"caption": "the man in white shirt", "predicate": "in", "target": {"coordinates": [316.17938232422, -2.8643417358398, 414.04016113281, 211.18438720703]}, "name": 162, "source": {"coordinates": [-4.14404296875, 130.69808959961, 306.71984863281, 271.47229003906]}, "seconds": 6.75, "object": "white shirt", "type": "relation", "subject": "the man"}, {"caption": "the man in white shirt", "predicate": "in", "target": {"coordinates": [24.223693847656, 40.272964477539, 698.95989990234, 377.94714355469]}, "name": 162, "source": {"coordinates": [316.17938232422, -2.8643417358398, 414.04016113281, 211.18438720703]}, "seconds": 6.75, "object": "white shirt", "type": "relation", "subject": "the man"}, {"caption": "the man wearing black shirt", "predicate": "wearing", "target": {"coordinates": [346.74032592773, 96.729339599609, 190.46060180664, 300.85144042969]}, "name": 162, "source": {"coordinates": [316.17938232422, -2.8643417358398, 414.04016113281, 211.18438720703]}, "seconds": 6.75, "object": "black shirt", "type": "relation", "subject": "the man"}, {"caption": "the man wearing black shirt", "predicate": "wearing", "target": {"coordinates": [214.47155761719, 61.551193237305, 194.03814697266, 342.97064208984]}, "name": 162, "source": {"coordinates": [316.17938232422, -2.8643417358398, 414.04016113281, 211.18438720703]}, "seconds": 6.75, "object": "black shirt", "type": "relation", "subject": "the man"}, {"caption": "the man wearing black shirt", "predicate": "wearing", "target": {"coordinates": [327.78262329102, 329.08309936523, 57.019287109375, 56.166625976562]}, "name": 162, "source": {"coordinates": [316.17938232422, -2.8643417358398, 414.04016113281, 211.18438720703]}, "seconds": 6.75, "object": "black shirt", "type": "relation", "subject": "the man"}, {"caption": "the man wearing white shirt", "predicate": "wearing", "target": {"coordinates": [7.5440368652344, -4.0870895385742, 392.7375793457, 193.44567871094]}, "name": 162, "source": {"coordinates": [316.17938232422, -2.8643417358398, 414.04016113281, 211.18438720703]}, "seconds": 6.75, "object": "white shirt", "type": "relation", "subject": "the man"}, {"caption": "the man wearing white shirt", "predicate": "wearing", "target": {"coordinates": [257.05209350586, 182.48709106445, 104.06707763672, 42.362121582031]}, "name": 162, "source": {"coordinates": [316.17938232422, -2.8643417358398, 414.04016113281, 211.18438720703]}, "seconds": 6.75, "object": "white shirt", "type": "relation", "subject": "the man"}, {"caption": "the man in white shirt", "predicate": "in", "target": {"coordinates": [-4.14404296875, 130.69808959961, 306.71984863281, 271.47229003906]}, "name": 162, "source": {"coordinates": [316.17938232422, -2.8643417358398, 414.04016113281, 211.18438720703]}, "seconds": 6.75, "object": "white shirt", "type": "relation", "subject": "the man"}]