[{"caption": "the hand on man", "predicate": "on", "target": {"coordinates": [121.66874694824, 1.5069274902344, 375.61938476562, 409.09219360352]}, "name": 165, "source": {"coordinates": [161.41064453125, 310.00439453125, 122.01412963867, 95.677185058594]}, "seconds": 6.875, "object": "man", "type": "relation", "subject": "the hand"}, {"caption": "the hand on man", "predicate": "on", "target": {"coordinates": [150.20739746094, 157.55383300781, 194.24066162109, 84.668182373047]}, "name": 165, "source": {"coordinates": [161.41064453125, 310.00439453125, 122.01412963867, 95.677185058594]}, "seconds": 6.875, "object": "man", "type": "relation", "subject": "the hand"}, {"caption": "the hand on man", "predicate": "on", "target": {"coordinates": [300.18731689453, 159.51992797852, 441.54919433594, 248.42065429688]}, "name": 165, "source": {"coordinates": [161.41064453125, 310.00439453125, 122.01412963867, 95.677185058594]}, "seconds": 6.875, "object": "man", "type": "relation", "subject": "the hand"}, {"caption": "the hand on man", "predicate": "on", "target": {"coordinates": [-0.29609680175781, -1.6667633056641, 308.82800292969, 278.4951171875]}, "name": 165, "source": {"coordinates": [161.41064453125, 310.00439453125, 122.01412963867, 95.677185058594]}, "seconds": 6.875, "object": "man", "type": "relation", "subject": "the hand"}, {"caption": "the man wearing black shirt", "predicate": "wearing", "target": {"coordinates": [325.88793945312, -7.0967864990234, 404.29321289062, 218.67715454102]}, "name": 165, "source": {"coordinates": [161.41064453125, 310.00439453125, 122.01412963867, 95.677185058594]}, "seconds": 6.875, "object": "black shirt", "type": "relation", "subject": "the man"}, {"caption": "the man wearing black shirt", "predicate": "wearing", "target": {"coordinates": [161.41064453125, 310.00439453125, 122.01412963867, 95.677185058594]}, "name": 165, "source": {"coordinates": [121.66874694824, 1.5069274902344, 375.61938476562, 409.09219360352]}, "seconds": 6.875, "object": "black shirt", "type": "relation", "subject": "the man"}, {"caption": "the man wearing white shirt", "predicate": "wearing", "target": {"coordinates": [150.20739746094, 157.55383300781, 194.24066162109, 84.668182373047]}, "name": 165, "source": {"coordinates": [121.66874694824, 1.5069274902344, 375.61938476562, 409.09219360352]}, "seconds": 6.875, "object": "white shirt", "type": "relation", "subject": "the man"}, {"caption": "the man wearing white shirt", "predicate": "wearing", "target": {"coordinates": [300.18731689453, 159.51992797852, 441.54919433594, 248.42065429688]}, "name": 165, "source": {"coordinates": [121.66874694824, 1.5069274902344, 375.61938476562, 409.09219360352]}, "seconds": 6.875, "object": "white shirt", "type": "relation", "subject": "the man"}, {"caption": "the man wearing white shirt", "predicate": "wearing", "target": {"coordinates": [-0.29609680175781, -1.6667633056641, 308.82800292969, 278.4951171875]}, "name": 165, "source": {"coordinates": [121.66874694824, 1.5069274902344, 375.61938476562, 409.09219360352]}, "seconds": 6.875, "object": "white shirt", "type": "relation", "subject": "the man"}, {"caption": "the man wearing black shirt", "predicate": "wearing", "target": {"coordinates": [325.88793945312, -7.0967864990234, 404.29321289062, 218.67715454102]}, "name": 165, "source": {"coordinates": [121.66874694824, 1.5069274902344, 375.61938476562, 409.09219360352]}, "seconds": 6.875, "object": "black shirt", "type": "relation", "subject": "the man"}, {"caption": "the man wearing black shirt", "predicate": "wearing", "target": {"coordinates": [161.41064453125, 310.00439453125, 122.01412963867, 95.677185058594]}, "name": 165, "source": {"coordinates": [150.20739746094, 157.55383300781, 194.24066162109, 84.668182373047]}, "seconds": 6.875, "object": "black shirt", "type": "relation", "subject": "the man"}, {"caption": "the logo on white shirt", "predicate": "on", "target": {"coordinates": [121.66874694824, 1.5069274902344, 375.61938476562, 409.09219360352]}, "name": 165, "source": {"coordinates": [150.20739746094, 157.55383300781, 194.24066162109, 84.668182373047]}, "seconds": 6.875, "object": "white shirt", "type": "relation", "subject": "the logo"}, {"caption": "the sign on wall", "predicate": "on", "target": {"coordinates": [300.18731689453, 159.51992797852, 441.54919433594, 248.42065429688]}, "name": 165, "source": {"coordinates": [150.20739746094, 157.55383300781, 194.24066162109, 84.668182373047]}, "seconds": 6.875, "object": "wall", "type": "relation", "subject": "the sign"}, {"caption": "the sign on wall", "predicate": "on", "target": {"coordinates": [-0.29609680175781, -1.6667633056641, 308.82800292969, 278.4951171875]}, "name": 165, "source": {"coordinates": [150.20739746094, 157.55383300781, 194.24066162109, 84.668182373047]}, "seconds": 6.875, "object": "wall", "type": "relation", "subject": "the sign"}, {"caption": "the man wearing white shirt", "predicate": "wearing", "target": {"coordinates": [325.88793945312, -7.0967864990234, 404.29321289062, 218.67715454102]}, "name": 165, "source": {"coordinates": [150.20739746094, 157.55383300781, 194.24066162109, 84.668182373047]}, "seconds": 6.875, "object": "white shirt", "type": "relation", "subject": "the man"}, {"caption": "the man wearing white shirt", "predicate": "wearing", "target": {"coordinates": [161.41064453125, 310.00439453125, 122.01412963867, 95.677185058594]}, "name": 165, "source": {"coordinates": [300.18731689453, 159.51992797852, 441.54919433594, 248.42065429688]}, "seconds": 6.875, "object": "white shirt", "type": "relation", "subject": "the man"}, {"caption": "the man wearing black shirt", "predicate": "wearing", "target": {"coordinates": [121.66874694824, 1.5069274902344, 375.61938476562, 409.09219360352]}, "name": 165, "source": {"coordinates": [300.18731689453, 159.51992797852, 441.54919433594, 248.42065429688]}, "seconds": 6.875, "object": "black shirt", "type": "relation", "subject": "the man"}, {"caption": "the man wearing black shirt", "predicate": "wearing", "target": {"coordinates": [150.20739746094, 157.55383300781, 194.24066162109, 84.668182373047]}, "name": 165, "source": {"coordinates": [300.18731689453, 159.51992797852, 441.54919433594, 248.42065429688]}, "seconds": 6.875, "object": "black shirt", "type": "relation", "subject": "the man"}, {"caption": "the man wearing white shirt", "predicate": "wearing", "target": {"coordinates": [-0.29609680175781, -1.6667633056641, 308.82800292969, 278.4951171875]}, "name": 165, "source": {"coordinates": [300.18731689453, 159.51992797852, 441.54919433594, 248.42065429688]}, "seconds": 6.875, "object": "white shirt", "type": "relation", "subject": "the man"}, {"caption": "the man wearing black shirt", "predicate": "wearing", "target": {"coordinates": [325.88793945312, -7.0967864990234, 404.29321289062, 218.67715454102]}, "name": 165, "source": {"coordinates": [300.18731689453, 159.51992797852, 441.54919433594, 248.42065429688]}, "seconds": 6.875, "object": "black shirt", "type": "relation", "subject": "the man"}, {"caption": "the man wearing black shirt", "predicate": "wearing", "target": {"coordinates": [161.41064453125, 310.00439453125, 122.01412963867, 95.677185058594]}, "name": 165, "source": {"coordinates": [-0.29609680175781, -1.6667633056641, 308.82800292969, 278.4951171875]}, "seconds": 6.875, "object": "black shirt", "type": "relation", "subject": "the man"}, {"caption": "the man wearing black shirt", "predicate": "wearing", "target": {"coordinates": [121.66874694824, 1.5069274902344, 375.61938476562, 409.09219360352]}, "name": 165, "source": {"coordinates": [-0.29609680175781, -1.6667633056641, 308.82800292969, 278.4951171875]}, "seconds": 6.875, "object": "black shirt", "type": "relation", "subject": "the man"}, {"caption": "the man wearing black shirt", "predicate": "wearing", "target": {"coordinates": [150.20739746094, 157.55383300781, 194.24066162109, 84.668182373047]}, "name": 165, "source": {"coordinates": [-0.29609680175781, -1.6667633056641, 308.82800292969, 278.4951171875]}, "seconds": 6.875, "object": "black shirt", "type": "relation", "subject": "the man"}, {"caption": "the man wearing white shirt", "predicate": "wearing", "target": {"coordinates": [300.18731689453, 159.51992797852, 441.54919433594, 248.42065429688]}, "name": 165, "source": {"coordinates": [-0.29609680175781, -1.6667633056641, 308.82800292969, 278.4951171875]}, "seconds": 6.875, "object": "white shirt", "type": "relation", "subject": "the man"}, {"caption": "the man wearing white shirt", "predicate": "wearing", "target": {"coordinates": [325.88793945312, -7.0967864990234, 404.29321289062, 218.67715454102]}, "name": 165, "source": {"coordinates": [-0.29609680175781, -1.6667633056641, 308.82800292969, 278.4951171875]}, "seconds": 6.875, "object": "white shirt", "type": "relation", "subject": "the man"}, {"caption": "the man wearing white shirt", "predicate": "wearing", "target": {"coordinates": [161.41064453125, 310.00439453125, 122.01412963867, 95.677185058594]}, "name": 165, "source": {"coordinates": [325.88793945312, -7.0967864990234, 404.29321289062, 218.67715454102]}, "seconds": 6.875, "object": "white shirt", "type": "relation", "subject": "the man"}, {"caption": "the man wearing black shirt", "predicate": "wearing", "target": {"coordinates": [121.66874694824, 1.5069274902344, 375.61938476562, 409.09219360352]}, "name": 165, "source": {"coordinates": [325.88793945312, -7.0967864990234, 404.29321289062, 218.67715454102]}, "seconds": 6.875, "object": "black shirt", "type": "relation", "subject": "the man"}, {"caption": "the man wearing white shirt", "predicate": "wearing", "target": {"coordinates": [150.20739746094, 157.55383300781, 194.24066162109, 84.668182373047]}, "name": 165, "source": {"coordinates": [325.88793945312, -7.0967864990234, 404.29321289062, 218.67715454102]}, "seconds": 6.875, "object": "white shirt", "type": "relation", "subject": "the man"}, {"caption": "the man wearing white shirt", "predicate": "wearing", "target": {"coordinates": [300.18731689453, 159.51992797852, 441.54919433594, 248.42065429688]}, "name": 165, "source": {"coordinates": [325.88793945312, -7.0967864990234, 404.29321289062, 218.67715454102]}, "seconds": 6.875, "object": "white shirt", "type": "relation", "subject": "the man"}, {"caption": "the man wearing white shirt", "predicate": "wearing", "target": {"coordinates": [-0.29609680175781, -1.6667633056641, 308.82800292969, 278.4951171875]}, "name": 165, "source": {"coordinates": [325.88793945312, -7.0967864990234, 404.29321289062, 218.67715454102]}, "seconds": 6.875, "object": "white shirt", "type": "relation", "subject": "the man"}]