[{"caption": "the man has a black hair", "predicate": "has", "target": {"coordinates": [-9.0208892822266, 2.2863464355469, 240.59523010254, 405.92758178711]}, "name": 333, "source": {"coordinates": [187.47477722168, -0.42753601074219, 383.55035400391, 412.19152832031]}, "seconds": 13.875, "object": "a black hair", "type": "relation", "subject": "the man"}, {"caption": "the man has head", "predicate": "has", "target": {"coordinates": [46.498481750488, 165.56935119629, 51.089202880859, 51.074645996094]}, "name": 333, "source": {"coordinates": [187.47477722168, -0.42753601074219, 383.55035400391, 412.19152832031]}, "seconds": 13.875, "object": "head", "type": "relation", "subject": "the man"}, {"caption": "the man wearing black shirt", "predicate": "wearing", "target": {"coordinates": [322.98846435547, 13.631065368652, 153.98889160156, 167.47955322266]}, "name": 333, "source": {"coordinates": [187.47477722168, -0.42753601074219, 383.55035400391, 412.19152832031]}, "seconds": 13.875, "object": "black shirt", "type": "relation", "subject": "the man"}, {"caption": "the man wearing black shirt", "predicate": "wearing", "target": {"coordinates": [496.31289672852, -7.9861755371094, 230.35116577148, 420.67462158203]}, "name": 333, "source": {"coordinates": [187.47477722168, -0.42753601074219, 383.55035400391, 412.19152832031]}, "seconds": 13.875, "object": "black shirt", "type": "relation", "subject": "the man"}, {"caption": "the man wearing black shirt", "predicate": "wearing", "target": {"coordinates": [409.82794189453, 127.47109985352, 186.20989990234, 275.71594238281]}, "name": 333, "source": {"coordinates": [187.47477722168, -0.42753601074219, 383.55035400391, 412.19152832031]}, "seconds": 13.875, "object": "black shirt", "type": "relation", "subject": "the man"}, {"caption": "the man wearing black shirt", "predicate": "wearing", "target": {"coordinates": [187.47477722168, -0.42753601074219, 383.55035400391, 412.19152832031]}, "name": 333, "source": {"coordinates": [-9.0208892822266, 2.2863464355469, 240.59523010254, 405.92758178711]}, "seconds": 13.875, "object": "black shirt", "type": "relation", "subject": "the man"}, {"caption": "the man has head", "predicate": "has", "target": {"coordinates": [46.498481750488, 165.56935119629, 51.089202880859, 51.074645996094]}, "name": 333, "source": {"coordinates": [-9.0208892822266, 2.2863464355469, 240.59523010254, 405.92758178711]}, "seconds": 13.875, "object": "head", "type": "relation", "subject": "the man"}, {"caption": "the man wearing black shirt", "predicate": "wearing", "target": {"coordinates": [322.98846435547, 13.631065368652, 153.98889160156, 167.47955322266]}, "name": 333, "source": {"coordinates": [-9.0208892822266, 2.2863464355469, 240.59523010254, 405.92758178711]}, "seconds": 13.875, "object": "black shirt", "type": "relation", "subject": "the man"}, {"caption": "the man wearing black shirt", "predicate": "wearing", "target": {"coordinates": [496.31289672852, -7.9861755371094, 230.35116577148, 420.67462158203]}, "name": 333, "source": {"coordinates": [-9.0208892822266, 2.2863464355469, 240.59523010254, 405.92758178711]}, "seconds": 13.875, "object": "black shirt", "type": "relation", "subject": "the man"}, {"caption": "the hand on man", "predicate": "on", "target": {"coordinates": [409.82794189453, 127.47109985352, 186.20989990234, 275.71594238281]}, "name": 333, "source": {"coordinates": [-9.0208892822266, 2.2863464355469, 240.59523010254, 405.92758178711]}, "seconds": 13.875, "object": "man", "type": "relation", "subject": "the hand"}, {"caption": "the hand on man", "predicate": "on", "target": {"coordinates": [187.47477722168, -0.42753601074219, 383.55035400391, 412.19152832031]}, "name": 333, "source": {"coordinates": [46.498481750488, 165.56935119629, 51.089202880859, 51.074645996094]}, "seconds": 13.875, "object": "man", "type": "relation", "subject": "the hand"}, {"caption": "the hand on a man", "predicate": "on", "target": {"coordinates": [-9.0208892822266, 2.2863464355469, 240.59523010254, 405.92758178711]}, "name": 333, "source": {"coordinates": [46.498481750488, 165.56935119629, 51.089202880859, 51.074645996094]}, "seconds": 13.875, "object": "a man", "type": "relation", "subject": "the hand"}, {"caption": "the hand on white shirt", "predicate": "on", "target": {"coordinates": [322.98846435547, 13.631065368652, 153.98889160156, 167.47955322266]}, "name": 333, "source": {"coordinates": [46.498481750488, 165.56935119629, 51.089202880859, 51.074645996094]}, "seconds": 13.875, "object": "white shirt", "type": "relation", "subject": "the hand"}, {"caption": "the hand on man", "predicate": "on", "target": {"coordinates": [496.31289672852, -7.9861755371094, 230.35116577148, 420.67462158203]}, "name": 333, "source": {"coordinates": [46.498481750488, 165.56935119629, 51.089202880859, 51.074645996094]}, "seconds": 13.875, "object": "man", "type": "relation", "subject": "the hand"}, {"caption": "the man wearing black shirt", "predicate": "wearing", "target": {"coordinates": [409.82794189453, 127.47109985352, 186.20989990234, 275.71594238281]}, "name": 333, "source": {"coordinates": [46.498481750488, 165.56935119629, 51.089202880859, 51.074645996094]}, "seconds": 13.875, "object": "black shirt", "type": "relation", "subject": "the man"}, {"caption": "the man wearing black shirt", "predicate": "wearing", "target": {"coordinates": [187.47477722168, -0.42753601074219, 383.55035400391, 412.19152832031]}, "name": 333, "source": {"coordinates": [322.98846435547, 13.631065368652, 153.98889160156, 167.47955322266]}, "seconds": 13.875, "object": "black shirt", "type": "relation", "subject": "the man"}, {"caption": "the man wearing black shirt", "predicate": "wearing", "target": {"coordinates": [-9.0208892822266, 2.2863464355469, 240.59523010254, 405.92758178711]}, "name": 333, "source": {"coordinates": [322.98846435547, 13.631065368652, 153.98889160156, 167.47955322266]}, "seconds": 13.875, "object": "black shirt", "type": "relation", "subject": "the man"}, {"caption": "the man wearing black hat", "predicate": "wearing", "target": {"coordinates": [46.498481750488, 165.56935119629, 51.089202880859, 51.074645996094]}, "name": 333, "source": {"coordinates": [322.98846435547, 13.631065368652, 153.98889160156, 167.47955322266]}, "seconds": 13.875, "object": "black hat", "type": "relation", "subject": "the man"}, {"caption": "the man wearing black shirt", "predicate": "wearing", "target": {"coordinates": [496.31289672852, -7.9861755371094, 230.35116577148, 420.67462158203]}, "name": 333, "source": {"coordinates": [322.98846435547, 13.631065368652, 153.98889160156, 167.47955322266]}, "seconds": 13.875, "object": "black shirt", "type": "relation", "subject": "the man"}, {"caption": "the man wearing black shirt", "predicate": "wearing", "target": {"coordinates": [409.82794189453, 127.47109985352, 186.20989990234, 275.71594238281]}, "name": 333, "source": {"coordinates": [322.98846435547, 13.631065368652, 153.98889160156, 167.47955322266]}, "seconds": 13.875, "object": "black shirt", "type": "relation", "subject": "the man"}, {"caption": "the man wearing black shirt", "predicate": "wearing", "target": {"coordinates": [187.47477722168, -0.42753601074219, 383.55035400391, 412.19152832031]}, "name": 333, "source": {"coordinates": [496.31289672852, -7.9861755371094, 230.35116577148, 420.67462158203]}, "seconds": 13.875, "object": "black shirt", "type": "relation", "subject": "the man"}, {"caption": "the man wearing black shirt", "predicate": "wearing", "target": {"coordinates": [-9.0208892822266, 2.2863464355469, 240.59523010254, 405.92758178711]}, "name": 333, "source": {"coordinates": [496.31289672852, -7.9861755371094, 230.35116577148, 420.67462158203]}, "seconds": 13.875, "object": "black shirt", "type": "relation", "subject": "the man"}, {"caption": "the man wearing black shirt", "predicate": "wearing", "target": {"coordinates": [46.498481750488, 165.56935119629, 51.089202880859, 51.074645996094]}, "name": 333, "source": {"coordinates": [496.31289672852, -7.9861755371094, 230.35116577148, 420.67462158203]}, "seconds": 13.875, "object": "black shirt", "type": "relation", "subject": "the man"}, {"caption": "the man wearing black shirt", "predicate": "wearing", "target": {"coordinates": [322.98846435547, 13.631065368652, 153.98889160156, 167.47955322266]}, "name": 333, "source": {"coordinates": [496.31289672852, -7.9861755371094, 230.35116577148, 420.67462158203]}, "seconds": 13.875, "object": "black shirt", "type": "relation", "subject": "the man"}, {"caption": "the man wearing black shirt", "predicate": "wearing", "target": {"coordinates": [409.82794189453, 127.47109985352, 186.20989990234, 275.71594238281]}, "name": 333, "source": {"coordinates": [496.31289672852, -7.9861755371094, 230.35116577148, 420.67462158203]}, "seconds": 13.875, "object": "black shirt", "type": "relation", "subject": "the man"}, {"caption": "the man wearing black shirt", "predicate": "wearing", "target": {"coordinates": [187.47477722168, -0.42753601074219, 383.55035400391, 412.19152832031]}, "name": 333, "source": {"coordinates": [409.82794189453, 127.47109985352, 186.20989990234, 275.71594238281]}, "seconds": 13.875, "object": "black shirt", "type": "relation", "subject": "the man"}, {"caption": "the man wearing black shirt", "predicate": "wearing", "target": {"coordinates": [-9.0208892822266, 2.2863464355469, 240.59523010254, 405.92758178711]}, "name": 333, "source": {"coordinates": [409.82794189453, 127.47109985352, 186.20989990234, 275.71594238281]}, "seconds": 13.875, "object": "black shirt", "type": "relation", "subject": "the man"}, {"caption": "the man wearing black hat", "predicate": "wearing", "target": {"coordinates": [46.498481750488, 165.56935119629, 51.089202880859, 51.074645996094]}, "name": 333, "source": {"coordinates": [409.82794189453, 127.47109985352, 186.20989990234, 275.71594238281]}, "seconds": 13.875, "object": "black hat", "type": "relation", "subject": "the man"}, {"caption": "the man wearing black shirt", "predicate": "wearing", "target": {"coordinates": [322.98846435547, 13.631065368652, 153.98889160156, 167.47955322266]}, "name": 333, "source": {"coordinates": [409.82794189453, 127.47109985352, 186.20989990234, 275.71594238281]}, "seconds": 13.875, "object": "black shirt", "type": "relation", "subject": "the man"}, {"caption": "the man wearing black shirt", "predicate": "wearing", "target": {"coordinates": [496.31289672852, -7.9861755371094, 230.35116577148, 420.67462158203]}, "name": 333, "source": {"coordinates": [409.82794189453, 127.47109985352, 186.20989990234, 275.71594238281]}, "seconds": 13.875, "object": "black shirt", "type": "relation", "subject": "the man"}]